edbogenerator/__init__.py
edbogenerator/generator.py
edbogenerator/vis.py
edbogenerator-0.1.2.dist-info/METADATA
edbogenerator-0.1.2.dist-info/WHEEL
edbogenerator-0.1.2.dist-info/RECORD
